{
  "metadata": {
    "symbol": "AAPL",
    "date": "2025-11-06",
    "analysis_date": "2025-11-06 13:32:56"
  },
  "technical_analysis": {
    "current_price": 270.14,
    "price_change_pct": 21.86,
    "price_trend": "Up",
    "volume_trend": "Below Average",
    "rsi_signal": "Neutral",
    "indicators": {
      "rsi": 67.56,
      "macd": 6.05,
      "macd_signal": 5.71,
      "bb_high": 278.74,
      "bb_mid": 260.41,
      "bb_low": 242.08
    }
  },
  "options_analysis": {
    "expiration": "2025-11-07",
    "put_call_ratio": 0.69,
    "total_put_volume": 108106,
    "total_call_volume": 157310,
    "sentiment": "Bullish"
  },
  "risk_analysis": {
    "atr": 5.07,
    "suggested_stop_loss": 260.01,
    "position_size": 9.87,
    "risk_per_trade": 100.0,
    "max_portfolio_risk": 500.0
  },
  "recommendations": [
    "The price trend is UP by 21.86% in the given period. Consider looking for buying opportunities on pullbacks.",
    "Low Put/Call Ratio of 0.69 indicates bullish sentiment. Traders are buying more calls than puts, which could indicate continued upward momentum.",
    "Based on your risk settings, consider a position size of 9.87 shares with a stop loss at $260.01 to limit risk to $100.00 per trade."
  ],
  "charts": {
    "price_chart": "reports/AAPL_price_chart.html",
    "rsi_chart": "reports/AAPL_rsi.html"
  }
}